{
    "A": "Bi", 
    "gllbsc_ind-gap": 0.0, 
    "B": "Au", 
    "anion": "ON2", 
    "CB_ind": 6.237007791528321, 
    "anion_idx": 2, 
    "heat_of_formation_all": 1.68, 
    "CB_dir": 6.237007791528321, 
    "filename": "/Users/ajain/Documents/papers_proposals/2012Paper_UNCOptimization/data/rawdata/abon2/d63d3d4e0ab1fe5f75197dd9f4b2a8ab50d9d9d9.json", 
    "sum_magnetic_moments": 0.5487916398581909, 
    "VB_dir": 6.237007791528321, 
    "VB_ind": 6.237007791528321, 
    "is_direct": true, 
    "gllbsc_dir-gap": 0.0, 
    "FermiLevel": 0.250901725299, 
    "XCFunctional": "RPBE", 
    "FermiWidth": 0.0018374654734, 
    "structure": {
        "lattice": {
            "a": 4.1797201052933, 
            "c": 4.1797201052933, 
            "b": 4.1797201052933, 
            "matrix": [
                [
                    4.1797201052933, 
                    0.0, 
                    0.0
                ], 
                [
                    0.0, 
                    4.1797201052933, 
                    0.0
                ], 
                [
                    0.0, 
                    0.0, 
                    4.1797201052933
                ]
            ], 
            "volume": 73.01996168555476, 
            "beta": 90.0, 
            "alpha": 90.0, 
            "gamma": 90.0
        }, 
        "sites": [
            {
                "label": "Bi", 
                "xyz": [
                    0.5210528156328296, 
                    0.0, 
                    6.025201667445415e-17
                ], 
                "abc": [
                    0.12466213107737896, 
                    0.0, 
                    1.4415323312714056e-17
                ], 
                "properties": {}, 
                "species": [
                    {
                        "occu": 1, 
                        "element": "Bi"
                    }
                ]
            }, 
            {
                "label": "Au", 
                "xyz": [
                    2.205607349978356, 
                    2.08986005264665, 
                    2.08986005264665
                ], 
                "abc": [
                    0.5276925952972595, 
                    0.5, 
                    0.5
                ], 
                "properties": {}, 
                "species": [
                    {
                        "occu": 1, 
                        "element": "Au"
                    }
                ]
            }, 
            {
                "label": "N", 
                "xyz": [
                    1.7198441227374668, 
                    5.0238946240965675e-18, 
                    2.08986005264665
                ], 
                "abc": [
                    0.41147351483163047, 
                    1.201969150454401e-18, 
                    0.5
                ], 
                "properties": {}, 
                "species": [
                    {
                        "occu": 1, 
                        "element": "N"
                    }
                ]
            }, 
            {
                "label": "N", 
                "xyz": [
                    1.7198441227374668, 
                    2.08986005264665, 
                    8.166570300667471e-20
                ], 
                "abc": [
                    0.41147351483163047, 
                    0.5, 
                    1.953855783387296e-20
                ], 
                "properties": {}, 
                "species": [
                    {
                        "occu": 1, 
                        "element": "N"
                    }
                ]
            }, 
            {
                "label": "O", 
                "xyz": [
                    0.025127721214448045, 
                    2.08986005264665, 
                    2.08986005264665
                ], 
                "abc": [
                    0.006011819112630457, 
                    0.5, 
                    0.5
                ], 
                "properties": {}, 
                "species": [
                    {
                        "occu": 1, 
                        "element": "O"
                    }
                ]
            }
        ], 
        "@class": "Structure", 
        "@module": "pymatgen.core.structure"
    }
}