{
    "A": "Hf", 
    "gllbsc_ind-gap": 0.0, 
    "B": "Na", 
    "anion": "N3", 
    "CB_ind": 5.181320942891161, 
    "anion_idx": 3, 
    "heat_of_formation_all": 3.12, 
    "CB_dir": 5.181320942891161, 
    "filename": "/Users/ajain/Documents/papers_proposals/2012Paper_UNCOptimization/data/rawdata/abn3/f11906c4e74c3f0cfb17a561973da322e5338dbe.json", 
    "sum_magnetic_moments": 3.2450017629359103, 
    "VB_dir": 5.181320942891161, 
    "VB_ind": 5.181320942891161, 
    "is_direct": true, 
    "gllbsc_dir-gap": 0.0, 
    "FermiLevel": 0.223626203028, 
    "XCFunctional": "RPBE", 
    "FermiWidth": 0.0018374654734, 
    "structure": {
        "lattice": {
            "a": 3.9387363017153554, 
            "c": 3.9387363017153554, 
            "b": 3.9387363017153554, 
            "matrix": [
                [
                    3.9387363017153554, 
                    0.0, 
                    0.0
                ], 
                [
                    0.0, 
                    3.9387363017153554, 
                    0.0
                ], 
                [
                    0.0, 
                    0.0, 
                    3.9387363017153554
                ]
            ], 
            "volume": 61.10415143365968, 
            "beta": 90.0, 
            "alpha": 90.0, 
            "gamma": 90.0
        }, 
        "sites": [
            {
                "label": "Hf", 
                "xyz": [
                    0.0, 
                    0.0, 
                    0.0
                ], 
                "abc": [
                    0.0, 
                    0.0, 
                    0.0
                ], 
                "properties": {}, 
                "species": [
                    {
                        "occu": 1, 
                        "element": "Hf"
                    }
                ]
            }, 
            {
                "label": "Na", 
                "xyz": [
                    1.9693681508576766, 
                    1.9693681508576766, 
                    1.9693681508576766
                ], 
                "abc": [
                    0.4999999999999997, 
                    0.4999999999999997, 
                    0.4999999999999997
                ], 
                "properties": {}, 
                "species": [
                    {
                        "occu": 1, 
                        "element": "Na"
                    }
                ]
            }, 
            {
                "label": "N", 
                "xyz": [
                    1.9693681508576766, 
                    0.0, 
                    1.9693681508576766
                ], 
                "abc": [
                    0.4999999999999997, 
                    0.0, 
                    0.4999999999999997
                ], 
                "properties": {}, 
                "species": [
                    {
                        "occu": 1, 
                        "element": "N"
                    }
                ]
            }, 
            {
                "label": "N", 
                "xyz": [
                    1.9693681508576766, 
                    1.9693681508576766, 
                    0.0
                ], 
                "abc": [
                    0.4999999999999997, 
                    0.4999999999999997, 
                    0.0
                ], 
                "properties": {}, 
                "species": [
                    {
                        "occu": 1, 
                        "element": "N"
                    }
                ]
            }, 
            {
                "label": "N", 
                "xyz": [
                    0.0, 
                    1.9693681508576766, 
                    1.9693681508576766
                ], 
                "abc": [
                    0.0, 
                    0.4999999999999997, 
                    0.4999999999999997
                ], 
                "properties": {}, 
                "species": [
                    {
                        "occu": 1, 
                        "element": "N"
                    }
                ]
            }
        ], 
        "@class": "Structure", 
        "@module": "pymatgen.core.structure"
    }
}