{
    "A": "Ir", 
    "gllbsc_ind-gap": 0.0, 
    "B": "Ru", 
    "anion": "OFN", 
    "CB_ind": 6.719033052243101, 
    "anion_idx": 5, 
    "heat_of_formation_all": 1.76, 
    "CB_dir": 6.719033052243101, 
    "filename": "/Users/ajain/Documents/papers_proposals/2012Paper_UNCOptimization/data/rawdata/abofn/682f0533d2868e3f4256ae4e73055a5a5d332987.json", 
    "sum_magnetic_moments": 1.5727613597874353, 
    "VB_dir": 6.719033052243101, 
    "VB_ind": 6.719033052243101, 
    "is_direct": true, 
    "gllbsc_dir-gap": 0.0, 
    "FermiLevel": 0.252460173865, 
    "XCFunctional": "RPBE", 
    "FermiWidth": 0.0036749309468, 
    "structure": {
        "lattice": {
            "a": 4.011403362639265, 
            "c": 4.011403362639265, 
            "b": 4.011403362639265, 
            "matrix": [
                [
                    4.011403362639265, 
                    0.0, 
                    0.0
                ], 
                [
                    0.0, 
                    4.011403362639265, 
                    0.0
                ], 
                [
                    0.0, 
                    0.0, 
                    4.011403362639265
                ]
            ], 
            "volume": 64.54892332969392, 
            "beta": 90.0, 
            "alpha": 90.0, 
            "gamma": 90.0
        }, 
        "sites": [
            {
                "label": "Ir", 
                "xyz": [
                    0.002859819268839042, 
                    0.0, 
                    0.0
                ], 
                "abc": [
                    0.0007129223890756902, 
                    0.0, 
                    0.0
                ], 
                "properties": {}, 
                "species": [
                    {
                        "occu": 1, 
                        "element": "Ir"
                    }
                ]
            }, 
            {
                "label": "Ru", 
                "xyz": [
                    2.0221803873593682, 
                    2.0057016813196333, 
                    2.0057016813196333
                ], 
                "abc": [
                    0.50410796535527, 
                    0.5000000000000002, 
                    0.5000000000000002
                ], 
                "properties": {}, 
                "species": [
                    {
                        "occu": 1, 
                        "element": "Ru"
                    }
                ]
            }, 
            {
                "label": "F", 
                "xyz": [
                    2.003829417305016, 
                    0.0, 
                    2.0057016813196333
                ], 
                "abc": [
                    0.49953326458464536, 
                    0.0, 
                    0.5000000000000002
                ], 
                "properties": {}, 
                "species": [
                    {
                        "occu": 1, 
                        "element": "F"
                    }
                ]
            }, 
            {
                "label": "N", 
                "xyz": [
                    2.0091368712151216, 
                    2.0057016813196333, 
                    0.0
                ], 
                "abc": [
                    0.5008563561389721, 
                    0.5000000000000002, 
                    0.0
                ], 
                "properties": {}, 
                "species": [
                    {
                        "occu": 1, 
                        "element": "N"
                    }
                ]
            }, 
            {
                "label": "O", 
                "xyz": [
                    0.0183113193656777, 
                    2.0057016813196333, 
                    2.0057016813196333
                ], 
                "abc": [
                    0.004564816277570736, 
                    0.5000000000000002, 
                    0.5000000000000002
                ], 
                "properties": {}, 
                "species": [
                    {
                        "occu": 1, 
                        "element": "O"
                    }
                ]
            }
        ], 
        "@class": "Structure", 
        "@module": "pymatgen.core.structure"
    }
}