{
    "A": "Os", 
    "gllbsc_ind-gap": 0.0, 
    "B": "Ba", 
    "anion": "N3", 
    "CB_ind": 5.500591294381255, 
    "anion_idx": 3, 
    "heat_of_formation_all": 4.08, 
    "CB_dir": 5.500591294381255, 
    "filename": "/Users/ajain/Documents/papers_proposals/2012Paper_UNCOptimization/data/rawdata/abn3/b8a11b221d2ffe72e8f5070e889c17e776c2ba35.json", 
    "sum_magnetic_moments": 5.217950435994238, 
    "VB_dir": 5.500591294381255, 
    "VB_ind": 5.500591294381255, 
    "is_direct": true, 
    "gllbsc_dir-gap": 0.0, 
    "FermiLevel": 0.227894334111, 
    "XCFunctional": "RPBE", 
    "FermiWidth": 0.0018374654734, 
    "structure": {
        "lattice": {
            "a": 4.412027226833418, 
            "c": 4.412027226833418, 
            "b": 4.412027226833418, 
            "matrix": [
                [
                    4.412027226833418, 
                    0.0, 
                    0.0
                ], 
                [
                    0.0, 
                    4.412027226833418, 
                    0.0
                ], 
                [
                    0.0, 
                    0.0, 
                    4.412027226833418
                ]
            ], 
            "volume": 85.8844525095196, 
            "beta": 90.0, 
            "alpha": 90.0, 
            "gamma": 90.0
        }, 
        "sites": [
            {
                "label": "Os", 
                "xyz": [
                    0.008522208404756227, 
                    0.0, 
                    3.337196186636031e-19
                ], 
                "abc": [
                    0.0019315856332266452, 
                    0.0, 
                    7.563861270709315e-20
                ], 
                "properties": {}, 
                "species": [
                    {
                        "occu": 1, 
                        "element": "Os"
                    }
                ]
            }, 
            {
                "label": "Ba", 
                "xyz": [
                    2.2128804772071557, 
                    2.206013613416709, 
                    2.206013613416709
                ], 
                "abc": [
                    0.5015563965128509, 
                    0.5, 
                    0.5
                ], 
                "properties": {}, 
                "species": [
                    {
                        "occu": 1, 
                        "element": "Ba"
                    }
                ]
            }, 
            {
                "label": "N", 
                "xyz": [
                    2.2150817767715103, 
                    0.0, 
                    2.206013613416709
                ], 
                "abc": [
                    0.5020553280586416, 
                    0.0, 
                    0.5
                ], 
                "properties": {}, 
                "species": [
                    {
                        "occu": 1, 
                        "element": "N"
                    }
                ]
            }, 
            {
                "label": "N", 
                "xyz": [
                    2.2150817767715103, 
                    2.206013613416709, 
                    1.1219760555173308e-18
                ], 
                "abc": [
                    0.5020553280586416, 
                    0.5, 
                    2.5429944055957035e-19
                ], 
                "properties": {}, 
                "species": [
                    {
                        "occu": 1, 
                        "element": "N"
                    }
                ]
            }, 
            {
                "label": "N", 
                "xyz": [
                    0.0068004714965635765, 
                    2.206013613416709, 
                    2.206013613416709
                ], 
                "abc": [
                    0.001541348488332966, 
                    0.5, 
                    0.5
                ], 
                "properties": {}, 
                "species": [
                    {
                        "occu": 1, 
                        "element": "N"
                    }
                ]
            }
        ], 
        "@class": "Structure", 
        "@module": "pymatgen.core.structure"
    }
}