{
    "A": "Pd", 
    "gllbsc_ind-gap": 0.0, 
    "B": "La", 
    "anion": "O2N", 
    "CB_ind": 5.60658309807317, 
    "anion_idx": 1, 
    "heat_of_formation_all": 2.1, 
    "CB_dir": 5.60658309807317, 
    "filename": "/Users/ajain/Documents/papers_proposals/2012Paper_UNCOptimization/data/rawdata/abo2n/812f80b64a344492b9c9897078f982f60c564a43.json", 
    "sum_magnetic_moments": 2.0020225926656248, 
    "VB_dir": 5.60658309807317, 
    "VB_ind": 5.60658309807317, 
    "is_direct": true, 
    "gllbsc_dir-gap": 0.0, 
    "FermiLevel": 0.146377262125, 
    "XCFunctional": "RPBE", 
    "FermiWidth": 0.0018374654734, 
    "structure": {
        "lattice": {
            "a": 4.562566491800143, 
            "c": 4.562566491800143, 
            "b": 4.562566491800143, 
            "matrix": [
                [
                    4.562566491800143, 
                    0.0, 
                    0.0
                ], 
                [
                    0.0, 
                    4.562566491800143, 
                    0.0
                ], 
                [
                    0.0, 
                    0.0, 
                    4.562566491800143
                ]
            ], 
            "volume": 94.97900593711215, 
            "beta": 90.0, 
            "alpha": 90.0, 
            "gamma": 90.0
        }, 
        "sites": [
            {
                "label": "Pd", 
                "xyz": [
                    0.0022013664708614043, 
                    3.362457009436355e-18, 
                    2.397086899885602e-19
                ], 
                "abc": [
                    0.00048248424977865114, 
                    7.369661385712125e-19, 
                    5.2538125289651185e-20
                ], 
                "properties": {}, 
                "species": [
                    {
                        "occu": 1, 
                        "element": "Pd"
                    }
                ]
            }, 
            {
                "label": "La", 
                "xyz": [
                    2.304966884640007, 
                    2.281283245900072, 
                    2.281283245900072
                ], 
                "abc": [
                    0.5051908588691254, 
                    0.5000000000000001, 
                    0.5000000000000001
                ], 
                "properties": {}, 
                "species": [
                    {
                        "occu": 1, 
                        "element": "La"
                    }
                ]
            }, 
            {
                "label": "N", 
                "xyz": [
                    2.28052657859285, 
                    1.3123222653389447e-19, 
                    2.281283245900072
                ], 
                "abc": [
                    0.49983415752765875, 
                    2.8762808557364673e-20, 
                    0.5000000000000001
                ], 
                "properties": {}, 
                "species": [
                    {
                        "occu": 1, 
                        "element": "N"
                    }
                ]
            }, 
            {
                "label": "O", 
                "xyz": [
                    2.278115764290676, 
                    2.281283245900072, 
                    1.0668035969177995e-19
                ], 
                "abc": [
                    0.4993057675729027, 
                    0.5000000000000001, 
                    2.3381655891153845e-20
                ], 
                "properties": {}, 
                "species": [
                    {
                        "occu": 1, 
                        "element": "O"
                    }
                ]
            }, 
            {
                "label": "O", 
                "xyz": [
                    0.022773107075553235, 
                    2.281283245900072, 
                    2.281283245900072
                ], 
                "abc": [
                    0.004991293193530686, 
                    0.5000000000000001, 
                    0.5000000000000001
                ], 
                "properties": {}, 
                "species": [
                    {
                        "occu": 1, 
                        "element": "O"
                    }
                ]
            }
        ], 
        "@class": "Structure", 
        "@module": "pymatgen.core.structure"
    }
}