{
    "A": "Sn", 
    "gllbsc_ind-gap": 0.0, 
    "B": "Ge", 
    "anion": "O2N", 
    "CB_ind": 6.057175124174678, 
    "anion_idx": 1, 
    "heat_of_formation_all": 0.62, 
    "CB_dir": 6.057175124174678, 
    "filename": "/Users/ajain/Documents/papers_proposals/2012Paper_UNCOptimization/data/rawdata/abo2n/947b3739c48cd1444ec423166a5760b6a8b90015.json", 
    "sum_magnetic_moments": 0.012390874296944075, 
    "VB_dir": 6.057175124174678, 
    "VB_ind": 6.057175124174678, 
    "is_direct": true, 
    "gllbsc_dir-gap": 0.0, 
    "FermiLevel": 0.287646367527, 
    "XCFunctional": "RPBE", 
    "FermiWidth": 0.0018374654734, 
    "structure": {
        "lattice": {
            "a": 3.901296161450145, 
            "c": 3.901296161450145, 
            "b": 3.901296161450145, 
            "matrix": [
                [
                    3.901296161450145, 
                    0.0, 
                    0.0
                ], 
                [
                    0.0, 
                    3.901296161450145, 
                    0.0
                ], 
                [
                    0.0, 
                    0.0, 
                    3.901296161450145
                ]
            ], 
            "volume": 59.37816350555142, 
            "beta": 90.0, 
            "alpha": 90.0, 
            "gamma": 90.0
        }, 
        "sites": [
            {
                "label": "Sn", 
                "xyz": [
                    0.5417416183129816, 
                    2.498881430990157e-18, 
                    0.0
                ], 
                "abc": [
                    0.13886195661485276, 
                    6.405259502424705e-19, 
                    0.0
                ], 
                "properties": {}, 
                "species": [
                    {
                        "occu": 1, 
                        "element": "Sn"
                    }
                ]
            }, 
            {
                "label": "Ge", 
                "xyz": [
                    2.10369037563051, 
                    1.950648080725073, 
                    1.950648080725073
                ], 
                "abc": [
                    0.5392285764966253, 
                    0.5000000000000001, 
                    0.5000000000000001
                ], 
                "properties": {}, 
                "species": [
                    {
                        "occu": 1, 
                        "element": "Ge"
                    }
                ]
            }, 
            {
                "label": "N", 
                "xyz": [
                    1.7419567392069069, 
                    8.39359294792296e-18, 
                    1.950648080725073
                ], 
                "abc": [
                    0.446507177901461, 
                    2.151488274810439e-18, 
                    0.5000000000000001
                ], 
                "properties": {}, 
                "species": [
                    {
                        "occu": 1, 
                        "element": "N"
                    }
                ]
            }, 
            {
                "label": "O", 
                "xyz": [
                    1.8105074821826947, 
                    1.950648080725073, 
                    0.0
                ], 
                "abc": [
                    0.46407845168814704, 
                    0.5000000000000001, 
                    0.0
                ], 
                "properties": {}, 
                "species": [
                    {
                        "occu": 1, 
                        "element": "O"
                    }
                ]
            }, 
            {
                "label": "O", 
                "xyz": [
                    0.021860121398948915, 
                    1.950648080725073, 
                    1.950648080725073
                ], 
                "abc": [
                    0.005603297082378725, 
                    0.5000000000000001, 
                    0.5000000000000001
                ], 
                "properties": {}, 
                "species": [
                    {
                        "occu": 1, 
                        "element": "O"
                    }
                ]
            }
        ], 
        "@class": "Structure", 
        "@module": "pymatgen.core.structure"
    }
}