{
    "A": "Ta", 
    "gllbsc_ind-gap": 0.0, 
    "B": "Hg", 
    "anion": "O2F", 
    "CB_ind": 6.611484868649611, 
    "anion_idx": 4, 
    "heat_of_formation_all": 2.08, 
    "CB_dir": 6.611484868649611, 
    "filename": "/Users/ajain/Documents/papers_proposals/2012Paper_UNCOptimization/data/rawdata/abo2f/a0eecbcf967ffdc17e6d6f7d0bc4c4a123fcddca.json", 
    "sum_magnetic_moments": 2.5150618122230353, 
    "VB_dir": 6.611484868649611, 
    "VB_ind": 6.611484868649611, 
    "is_direct": true, 
    "gllbsc_dir-gap": 0.0, 
    "FermiLevel": 0.187525164388, 
    "XCFunctional": "RPBE", 
    "FermiWidth": 0.0036749309468, 
    "structure": {
        "lattice": {
            "a": 4.330862474119166, 
            "c": 4.330862474119166, 
            "b": 4.330862474119166, 
            "matrix": [
                [
                    4.330862474119166, 
                    0.0, 
                    0.0
                ], 
                [
                    0.0, 
                    4.330862474119166, 
                    0.0
                ], 
                [
                    0.0, 
                    0.0, 
                    4.330862474119166
                ]
            ], 
            "volume": 81.23125798644233, 
            "beta": 90.0, 
            "alpha": 90.0, 
            "gamma": 90.0
        }, 
        "sites": [
            {
                "label": "Ta", 
                "xyz": [
                    0.0019342350588788635, 
                    0.0, 
                    0.0
                ], 
                "abc": [
                    0.00044661659667968526, 
                    0.0, 
                    0.0
                ], 
                "properties": {}, 
                "species": [
                    {
                        "occu": 1, 
                        "element": "Ta"
                    }
                ]
            }, 
            {
                "label": "Hg", 
                "xyz": [
                    2.1881897317232735, 
                    2.1654312370595825, 
                    2.1654312370595825
                ], 
                "abc": [
                    0.5052549566742637, 
                    0.4999999999999999, 
                    0.4999999999999999
                ], 
                "properties": {}, 
                "species": [
                    {
                        "occu": 1, 
                        "element": "Hg"
                    }
                ]
            }, 
            {
                "label": "F", 
                "xyz": [
                    2.1619900119806137, 
                    0.0, 
                    2.1654312370595825
                ], 
                "abc": [
                    0.4992054180663704, 
                    0.0, 
                    0.4999999999999999
                ], 
                "properties": {}, 
                "species": [
                    {
                        "occu": 1, 
                        "element": "F"
                    }
                ]
            }, 
            {
                "label": "O", 
                "xyz": [
                    2.16623581585703, 
                    2.1654312370595825, 
                    0.0
                ], 
                "abc": [
                    0.5001857779604536, 
                    0.4999999999999999, 
                    0.0
                ], 
                "properties": {}, 
                "species": [
                    {
                        "occu": 1, 
                        "element": "O"
                    }
                ]
            }, 
            {
                "label": "O", 
                "xyz": [
                    0.02129914063789079, 
                    2.1654312370595825, 
                    2.1654312370595825
                ], 
                "abc": [
                    0.004917990530794383, 
                    0.4999999999999999, 
                    0.4999999999999999
                ], 
                "properties": {}, 
                "species": [
                    {
                        "occu": 1, 
                        "element": "O"
                    }
                ]
            }
        ], 
        "@class": "Structure", 
        "@module": "pymatgen.core.structure"
    }
}