{
    "A": "Tl", 
    "gllbsc_ind-gap": 0.0, 
    "B": "Au", 
    "anion": "O2N", 
    "CB_ind": 6.6554052379162885, 
    "anion_idx": 1, 
    "heat_of_formation_all": 1.86, 
    "CB_dir": 6.6554052379162885, 
    "filename": "/Users/ajain/Documents/papers_proposals/2012Paper_UNCOptimization/data/rawdata/abo2n/42fa3f7ad32d318962130841ad064c938507b361.json", 
    "sum_magnetic_moments": 1.1125193950679986, 
    "VB_dir": 6.6554052379162885, 
    "VB_ind": 6.6554052379162885, 
    "is_direct": true, 
    "gllbsc_dir-gap": 0.0, 
    "FermiLevel": 0.19549117686, 
    "XCFunctional": "RPBE", 
    "FermiWidth": 0.0018374654734, 
    "structure": {
        "lattice": {
            "a": 4.204278011688529, 
            "c": 4.204278011688529, 
            "b": 4.204278011688529, 
            "matrix": [
                [
                    4.204278011688529, 
                    0.0, 
                    0.0
                ], 
                [
                    0.0, 
                    4.204278011688529, 
                    0.0
                ], 
                [
                    0.0, 
                    0.0, 
                    4.204278011688529
                ]
            ], 
            "volume": 74.31462305428897, 
            "beta": 90.0, 
            "alpha": 90.0, 
            "gamma": 90.0
        }, 
        "sites": [
            {
                "label": "Tl", 
                "xyz": [
                    0.0028076718638886285, 
                    0.0, 
                    0.0
                ], 
                "abc": [
                    0.000667813083740627, 
                    0.0, 
                    0.0
                ], 
                "properties": {}, 
                "species": [
                    {
                        "occu": 1, 
                        "element": "Tl"
                    }
                ]
            }, 
            {
                "label": "Au", 
                "xyz": [
                    2.1281963406150877, 
                    2.102139005844265, 
                    2.102139005844265
                ], 
                "abc": [
                    0.5061978143924784, 
                    0.5000000000000001, 
                    0.5000000000000001
                ], 
                "properties": {}, 
                "species": [
                    {
                        "occu": 1, 
                        "element": "Au"
                    }
                ]
            }, 
            {
                "label": "N", 
                "xyz": [
                    2.0981719703199126, 
                    0.0, 
                    2.102139005844265
                ], 
                "abc": [
                    0.4990564288295582, 
                    0.0, 
                    0.5000000000000001
                ], 
                "properties": {}, 
                "species": [
                    {
                        "occu": 1, 
                        "element": "N"
                    }
                ]
            }, 
            {
                "label": "O", 
                "xyz": [
                    2.102275810517272, 
                    2.102139005844265, 
                    0.0
                ], 
                "abc": [
                    0.5000325393974012, 
                    0.5000000000000001, 
                    0.0
                ], 
                "properties": {}, 
                "species": [
                    {
                        "occu": 1, 
                        "element": "O"
                    }
                ]
            }, 
            {
                "label": "O", 
                "xyz": [
                    0.020013250737467236, 
                    2.102139005844265, 
                    2.102139005844265
                ], 
                "abc": [
                    0.0047602110711583235, 
                    0.5000000000000001, 
                    0.5000000000000001
                ], 
                "properties": {}, 
                "species": [
                    {
                        "occu": 1, 
                        "element": "O"
                    }
                ]
            }
        ], 
        "@class": "Structure", 
        "@module": "pymatgen.core.structure"
    }
}