{
    "A": "Tl", 
    "gllbsc_ind-gap": 0.0, 
    "B": "Cu", 
    "anion": "N3", 
    "CB_ind": 6.238651388072569, 
    "anion_idx": 3, 
    "heat_of_formation_all": 2.16, 
    "CB_dir": 6.238651388072569, 
    "filename": "/Users/ajain/Documents/papers_proposals/2012Paper_UNCOptimization/data/rawdata/abn3/fa9dfe5870ef1af0f64edf51f7ad57b0f52ef21f.json", 
    "sum_magnetic_moments": 3.4637436543957176, 
    "VB_dir": 6.238651388072569, 
    "VB_ind": 6.238651388072569, 
    "is_direct": true, 
    "gllbsc_dir-gap": 0.0, 
    "FermiLevel": 0.257579917025, 
    "XCFunctional": "RPBE", 
    "FermiWidth": 0.0018374654734, 
    "structure": {
        "lattice": {
            "a": 3.950643970344568, 
            "c": 3.950643970344568, 
            "b": 3.950643970344568, 
            "matrix": [
                [
                    3.950643970344568, 
                    0.0, 
                    0.0
                ], 
                [
                    0.0, 
                    3.950643970344568, 
                    0.0
                ], 
                [
                    0.0, 
                    0.0, 
                    3.950643970344568
                ]
            ], 
            "volume": 61.66002255633941, 
            "beta": 90.0, 
            "alpha": 90.0, 
            "gamma": 90.0
        }, 
        "sites": [
            {
                "label": "Tl", 
                "xyz": [
                    0.0, 
                    0.0, 
                    0.0
                ], 
                "abc": [
                    0.0, 
                    0.0, 
                    0.0
                ], 
                "properties": {}, 
                "species": [
                    {
                        "occu": 1, 
                        "element": "Tl"
                    }
                ]
            }, 
            {
                "label": "Cu", 
                "xyz": [
                    1.975321985172284, 
                    1.975321985172284, 
                    1.975321985172284
                ], 
                "abc": [
                    0.5, 
                    0.5, 
                    0.5
                ], 
                "properties": {}, 
                "species": [
                    {
                        "occu": 1, 
                        "element": "Cu"
                    }
                ]
            }, 
            {
                "label": "N", 
                "xyz": [
                    1.975321985172284, 
                    0.0, 
                    1.975321985172284
                ], 
                "abc": [
                    0.5, 
                    0.0, 
                    0.5
                ], 
                "properties": {}, 
                "species": [
                    {
                        "occu": 1, 
                        "element": "N"
                    }
                ]
            }, 
            {
                "label": "N", 
                "xyz": [
                    1.975321985172284, 
                    1.975321985172284, 
                    0.0
                ], 
                "abc": [
                    0.5, 
                    0.5, 
                    0.0
                ], 
                "properties": {}, 
                "species": [
                    {
                        "occu": 1, 
                        "element": "N"
                    }
                ]
            }, 
            {
                "label": "N", 
                "xyz": [
                    0.0, 
                    1.975321985172284, 
                    1.975321985172284
                ], 
                "abc": [
                    0.0, 
                    0.5, 
                    0.5
                ], 
                "properties": {}, 
                "species": [
                    {
                        "occu": 1, 
                        "element": "N"
                    }
                ]
            }
        ], 
        "@class": "Structure", 
        "@module": "pymatgen.core.structure"
    }
}