{
    "A": "W", 
    "gllbsc_ind-gap": 0.0, 
    "B": "Na", 
    "anion": "O2N", 
    "CB_ind": 5.52948112531335, 
    "anion_idx": 1, 
    "heat_of_formation_all": 1.44, 
    "CB_dir": 5.52948112531335, 
    "filename": "/Users/ajain/Documents/papers_proposals/2012Paper_UNCOptimization/data/rawdata/abo2n/851f0af3d9b7466fb5f3ca5249cf3a150ef03233.json", 
    "sum_magnetic_moments": -0.00979038082838887, 
    "VB_dir": 5.52948112531335, 
    "VB_ind": 5.52948112531335, 
    "is_direct": true, 
    "gllbsc_dir-gap": 0.0, 
    "FermiLevel": 0.177101808803, 
    "XCFunctional": "RPBE", 
    "FermiWidth": 0.0018374654734, 
    "structure": {
        "lattice": {
            "a": 3.9803143972828505, 
            "c": 3.9803143972828505, 
            "b": 3.9803143972828505, 
            "matrix": [
                [
                    3.9803143972828505, 
                    0.0, 
                    0.0
                ], 
                [
                    0.0, 
                    3.9803143972828505, 
                    0.0
                ], 
                [
                    0.0, 
                    0.0, 
                    3.9803143972828505
                ]
            ], 
            "volume": 63.05973371640595, 
            "beta": 90.0, 
            "alpha": 90.0, 
            "gamma": 90.0
        }, 
        "sites": [
            {
                "label": "W", 
                "xyz": [
                    1.025681356577755, 
                    7.490220161292939e-16, 
                    3.463391187882772e-17
                ], 
                "abc": [
                    0.25768852763940786, 
                    1.8818162119068068e-16, 
                    8.701300556174772e-18
                ], 
                "properties": {}, 
                "species": [
                    {
                        "occu": 1, 
                        "element": "W"
                    }
                ]
            }, 
            {
                "label": "Na", 
                "xyz": [
                    2.356543207483301, 
                    1.9901571986414253, 
                    1.9901571986414253
                ], 
                "abc": [
                    0.5920495147549119, 
                    0.5, 
                    0.5
                ], 
                "properties": {}, 
                "species": [
                    {
                        "occu": 1, 
                        "element": "Na"
                    }
                ]
            }, 
            {
                "label": "N", 
                "xyz": [
                    0.6626528092742964, 
                    4.9479671044664735e-17, 
                    1.9901571986414253
                ], 
                "abc": [
                    0.16648252955260376, 
                    1.2431096166283217e-17, 
                    0.5
                ], 
                "properties": {}, 
                "species": [
                    {
                        "occu": 1, 
                        "element": "N"
                    }
                ]
            }, 
            {
                "label": "O", 
                "xyz": [
                    1.7460180097263807, 
                    1.9901571986414253, 
                    0.0
                ], 
                "abc": [
                    0.4386633404934782, 
                    0.5, 
                    0.0
                ], 
                "properties": {}, 
                "species": [
                    {
                        "occu": 1, 
                        "element": "O"
                    }
                ]
            }, 
            {
                "label": "O", 
                "xyz": [
                    0.3122931529012285, 
                    1.9901571986414253, 
                    1.9901571986414253
                ], 
                "abc": [
                    0.07845941846061569, 
                    0.5, 
                    0.5
                ], 
                "properties": {}, 
                "species": [
                    {
                        "occu": 1, 
                        "element": "O"
                    }
                ]
            }
        ], 
        "@class": "Structure", 
        "@module": "pymatgen.core.structure"
    }
}