{
    "A": "Y", 
    "gllbsc_ind-gap": 0.0, 
    "B": "Zr", 
    "anion": "ON2", 
    "CB_ind": 5.40693530168359, 
    "anion_idx": 2, 
    "heat_of_formation_all": 0.56, 
    "CB_dir": 5.40693530168359, 
    "filename": "/Users/ajain/Documents/papers_proposals/2012Paper_UNCOptimization/data/rawdata/abon2/b87c94ab34d91c15dddb59275efdf80b45ba8ba4.json", 
    "sum_magnetic_moments": -0.4189222216343599, 
    "VB_dir": 5.40693530168359, 
    "VB_ind": 5.40693530168359, 
    "is_direct": true, 
    "gllbsc_dir-gap": 0.0, 
    "FermiLevel": 0.253953263237, 
    "XCFunctional": "RPBE", 
    "FermiWidth": 0.0018374654734, 
    "structure": {
        "lattice": {
            "a": 4.219836194473227, 
            "c": 4.219836194473227, 
            "b": 4.219836194473227, 
            "matrix": [
                [
                    4.219836194473227, 
                    0.0, 
                    0.0
                ], 
                [
                    0.0, 
                    4.219836194473227, 
                    0.0
                ], 
                [
                    0.0, 
                    0.0, 
                    4.219836194473227
                ]
            ], 
            "volume": 75.14269699666293, 
            "beta": 90.0, 
            "alpha": 90.0, 
            "gamma": 90.0
        }, 
        "sites": [
            {
                "label": "Y", 
                "xyz": [
                    0.7325808873001279, 
                    4.092559265114666e-18, 
                    0.0
                ], 
                "abc": [
                    0.17360410535830714, 
                    9.69838419433139e-19, 
                    0.0
                ], 
                "properties": {}, 
                "species": [
                    {
                        "occu": 1, 
                        "element": "Y"
                    }
                ]
            }, 
            {
                "label": "Zr", 
                "xyz": [
                    2.2576851913963014, 
                    2.1099180972366134, 
                    2.1099180972366134
                ], 
                "abc": [
                    0.5350172583365251, 
                    0.5, 
                    0.5
                ], 
                "properties": {}, 
                "species": [
                    {
                        "occu": 1, 
                        "element": "Zr"
                    }
                ]
            }, 
            {
                "label": "N", 
                "xyz": [
                    1.8137040255074866, 
                    1.2581759015422231e-17, 
                    2.1099180972366134
                ], 
                "abc": [
                    0.4298043672602547, 
                    2.9815752165690037e-18, 
                    0.5
                ], 
                "properties": {}, 
                "species": [
                    {
                        "occu": 1, 
                        "element": "N"
                    }
                ]
            }, 
            {
                "label": "N", 
                "xyz": [
                    1.8137040255074866, 
                    2.1099180972366134, 
                    0.0
                ], 
                "abc": [
                    0.4298043672602547, 
                    0.5, 
                    0.0
                ], 
                "properties": {}, 
                "species": [
                    {
                        "occu": 1, 
                        "element": "N"
                    }
                ]
            }, 
            {
                "label": "O", 
                "xyz": [
                    0.02488793803285654, 
                    2.1099180972366134, 
                    2.1099180972366134
                ], 
                "abc": [
                    0.00589784458113625, 
                    0.5, 
                    0.5
                ], 
                "properties": {}, 
                "species": [
                    {
                        "occu": 1, 
                        "element": "O"
                    }
                ]
            }
        ], 
        "@class": "Structure", 
        "@module": "pymatgen.core.structure"
    }
}